srental/__init__.py
srental/app.py
srental/config.py
srental/controllers/__init__.py
srental/controllers/spaceship.py
srental/services/__init__.py
srental/services/contract.py
srental/tests/__init__.py
srental/tests/test_contract.py
srental-0.0.1.dist-info/METADATA
srental-0.0.1.dist-info/WHEEL
srental-0.0.1.dist-info/top_level.txt
srental-0.0.1.dist-info/RECORD
