Metadata-Version: 2.1
Name: srental
Version: 0.0.1
Summary: Used to optimize the profitability of a small rental company with a single spaceship to rent.
Home-page: UNKNOWN
Author: MingXing Xiao
Author-email: xiaomixin@gmail.com
License: Apache License 2.0
Platform: UNKNOWN
Classifier: Development Status :: 3 - Alpha
Classifier: Programming Language :: Python :: 3
Classifier: Operating System :: OS Independent
Requires-Python: >=3.10
Requires-Dist: flask (==2.2.3)
Requires-Dist: python-dotenv (==1.0.0)
